setup.py
sqinsta/__init__.py
sqinsta/functions.py
sqinsta.egg-info/PKG-INFO
sqinsta.egg-info/SOURCES.txt
sqinsta.egg-info/dependency_links.txt
sqinsta.egg-info/entry_points.txt
sqinsta.egg-info/not-zip-safe
sqinsta.egg-info/requires.txt
sqinsta.egg-info/top_level.txt