Metadata-Version: 1.0
Name: sqinsta
Version: 0.1
Summary: Download Insagram profile photos from command line
Home-page: https://github.com/saqirzzq/instaPy
Author: Saqib Razzaq
Author-email: saqi.cb@gmail.com
License: MIT
Platform: UNKNOWN
